snakedeploy/__init__.py
snakedeploy/_version.py
snakedeploy/client.py
snakedeploy/collect_files.py
snakedeploy/conda.py
snakedeploy/conda_version.py
snakedeploy/deploy.py
snakedeploy/exceptions.py
snakedeploy/logger.py
snakedeploy/providers.py
snakedeploy/snakemake_wrappers.py
snakedeploy/utils.py
snakedeploy/scaffold_plugins/__init__.py
snakedeploy/scaffold_plugins/common.py
snakedeploy/scaffold_plugins/executor_plugins.py
snakedeploy/scaffold_plugins/logger_plugins.py
snakedeploy/scaffold_plugins/report_plugins.py
snakedeploy/scaffold_plugins/scheduler_plugins.py
snakedeploy/scaffold_plugins/software_deployment_plugins.py
snakedeploy/scaffold_plugins/storage_plugins.py
snakedeploy/templates/post-instructions.txt.jinja
snakedeploy/templates/use_module.smk.jinja
snakedeploy/templates/plugins/ci.yml.j2
snakedeploy/templates/plugins/conventional_prs.yml.j2
snakedeploy/templates/plugins/release_please.yml.j2
snakedeploy/templates/plugins/setup.cfg.j2
snakedeploy/templates/plugins/executor-plugins/init.py
snakedeploy/templates/plugins/executor-plugins/tests.py.j2
snakedeploy/templates/plugins/logger-plugins/init.py
snakedeploy/templates/plugins/logger-plugins/tests.py
snakedeploy/templates/plugins/report-plugins/init.py
snakedeploy/templates/plugins/report-plugins/tests.py
snakedeploy/templates/plugins/scheduler-plugins/init.py
snakedeploy/templates/plugins/scheduler-plugins/tests.py
snakedeploy/templates/plugins/software-deployment-plugins/init.py
snakedeploy/templates/plugins/software-deployment-plugins/tests.py
snakedeploy/templates/plugins/storage-plugins/init.py
snakedeploy/templates/plugins/storage-plugins/tests.py
snakedeploy-0.14.0.dist-info/METADATA
snakedeploy-0.14.0.dist-info/WHEEL
snakedeploy-0.14.0.dist-info/entry_points.txt
snakedeploy-0.14.0.dist-info/licenses/LICENSE
snakedeploy-0.14.0.dist-info/RECORD
