Metadata-Version: 2.4
Name: snakedeploy
Version: 0.14.0
Summary: Deployment and maintenance related toolbox for Snakemake
Project-URL: Homepage, https://snakedeploy.readthedocs.io
Project-URL: Repository, https://github.com/snakemake/snakedeploy
Project-URL: Documentation, https://snakedeploy.readthedocs.io
Author-email: Johannes Koester <johannes.koester@uni-due.de>, Vanessa Sochat <vsochat@stanford.edu>
License-Expression: MPL-2.0
License-File: LICENSE
Requires-Python: <3.13,>=3.11
Requires-Dist: jinja2>=3.1.6
Requires-Dist: packaging>=25.0
Requires-Dist: pandas>=2.3.1
Requires-Dist: pygithub>=2.6.1
Requires-Dist: pyyaml>=6.0.2
Requires-Dist: requests>=2.32.4
Requires-Dist: reretry>=0.11.8
Requires-Dist: toml>=0.10.2
